conditor/__init__.py
conditor/__main__.py
conditor/action.py
conditor/build.py
conditor/config.py
conditor/project.py
conditor/recipe.py
conditor/cli/__init__.py
conditor/compose/__init__.py
conditor/compose/file_tree.py
conditor/compose/sfs.py
conditor/docs_baker/__init__.py
conditor/docs_baker/build.py
conditor/docs_baker/recipe.py
conditor/py3pkg/__init__.py
conditor/py3pkg/build.py
conditor/py3pkg/recipe.py
conditor/sphinx/__init__.py
conditor/sphinx/build.py
conditor/sphinx/recipe.py
conditor/util/__init__.py
conditor/util/actions.py
Conditor-0.0.3.dist-info/METADATA
Conditor-0.0.3.dist-info/WHEEL
Conditor-0.0.3.dist-info/entry_points.txt
Conditor-0.0.3.dist-info/top_level.txt
Conditor-0.0.3.dist-info/RECORD
