Metadata-Version: 2.1
Name: Conditor
Version: 0.0.3
Summary: Conditor Package
Author-email: Sophia Roger Hürzeler <srh@srhuerzeler.net>
